pycanal/__init__.py
pycanal/client.py
pycanal/connector.py
pycanal/example.py
pycanal/protocol/CanalProtocol_pb2.py
pycanal/protocol/EntryProtocol_pb2.py
pycanal/protocol/__init__.py
py3canal-1.0.4.dist-info/METADATA
py3canal-1.0.4.dist-info/WHEEL
py3canal-1.0.4.dist-info/top_level.txt
py3canal-1.0.4.dist-info/RECORD
