Metadata-Version: 2.1
Name: py3canal
Version: 1.0.4
Summary: UNKNOWN
Home-page: https://github.com/vallee11/canal-python
Author: vallee
Author-email: xph_wangly10@163.com
License: MIT
Platform: UNKNOWN
